ipa_utils/__init__.py
ipa_utils/base.py
ipa_utils/cli.py
tests/__init__.py
tests/test_ipaUtils.py
ipa_utils-0.2.3.dist-info/LICENSE
ipa_utils-0.2.3.dist-info/METADATA
ipa_utils-0.2.3.dist-info/WHEEL
ipa_utils-0.2.3.dist-info/entry_points.txt
ipa_utils-0.2.3.dist-info/top_level.txt
ipa_utils-0.2.3.dist-info/RECORD
