Metadata-Version: 2.1
Name: ipa-utils
Version: 0.2.3
Summary: Freeipa command line utils. Use sub-command to do real work.
Author: Le ZhengJia
Author-email: lezhengjia@zencore.cn
Maintainer: Le ZhengJia
Maintainer-email: lezhengjia@zencore.cn
License: MIT
Keywords: ipa-utils
Classifier: Development Status :: 5 - Production/Stable
Classifier: Intended Audience :: Developers
Classifier: Topic :: Software Development :: Libraries :: Python Modules
Classifier: License :: OSI Approved :: MIT License
Classifier: Programming Language :: Python :: 3
Classifier: Programming Language :: Python :: 3 :: Only
License-File: LICENSE
Requires-Dist: click
Requires-Dist: ldap3 >=2.7
Requires-Dist: PyYAML
